Metadata-Version: 2.1
Name: senaite.health
Version: 1.2.5
Summary: SENAITE Health
Home-page: https://github.com/senaite/senaite.health
Author: RIDING BYTES & NARALABS
Author-email: senaite@senaite.com
License: GPLv2
Keywords: lims,lis,senaite,opensource,health
Platform: UNKNOWN
Classifier: Development Status :: 5 - Production/Stable
Classifier: Environment :: Web Environment
Classifier: Framework :: Plone
Classifier: Framework :: Zope2
Classifier: Programming Language :: Python
Provides-Extra: test
